knust_service/__init__.py
knust_service/cli_knust_service.py
knust_service/configuration.py
knust_service/gpio_configure.py
knust_service/hardware_factory.py
knust_service/hardware_interface.py
knust_service/hardware_raspberry.py
knust_service/hardware_simulator.py
knust_service/knust_dbus_client.py
knust_service/knust_dbus_service.py
knust_service/service.py
knust_service/session.py
knust_service/string_format_helpers.py
knust-0.6.202302122114.dist-info/LICENSE
knust-0.6.202302122114.dist-info/METADATA
knust-0.6.202302122114.dist-info/WHEEL
knust-0.6.202302122114.dist-info/entry_points.txt
knust-0.6.202302122114.dist-info/top_level.txt
knust-0.6.202302122114.dist-info/RECORD
