Metadata-Version: 2.1
Name: knust
Version: 0.6.202302122114
Summary: Knust is a Python module to manage Raspberry Pi based thermostats
Home-page: https://gitlab.com/mirkoboehm/brot
Author: Mirko Boehm
Author-email: mirko@kde.org
License: UNKNOWN
Platform: UNKNOWN
Classifier: Programming Language :: Python :: 3
Classifier: License :: OSI Approved :: Apache Software License
Classifier: Operating System :: OS Independent
Classifier: Development Status :: 4 - Beta
Requires-Python: >=3.6
License-File: LICENSE
Requires-Dist: Click
Requires-Dist: humanize
Requires-Dist: pydbus
Requires-Dist: pygi
Requires-Dist: pyyaml
Requires-Dist: rpi-thingamajigs (>=0.6)
